Workbook

Sheet Assumptions
A1: CivFlow — 5-Year Financial Projection: Assumptions
A2: All figures are illustrative planning assumptions for a pre-launch product, not guarantees or forecasts. Blue = input you can change. Yellow = key lever worth stress-testing first. AUD throughout.
A4: PRICING
A5: Price per customer (per month) | B5: 200 | F5: Positioned above Buildxact's ~$199/mo entry tier and well below Buildertrend's ~$499/mo, reflecting CivFlow's QBCC-compliance-specific feature set (DTRs, deposit caps, MFR reminders, AI document filing). Sources: buildertrend.com/pricing; builtsimple.com.au 2026 comparison.
A7: MARKET SIZING — QUEENSLAND
A8: QBCC total licensees (all classes) | B8: 122000 | F8: Source: QBCC Licensed Contractors Register, data.qld.gov.au (current as at 04/08/2025). Covers builders, trade contractors, designers, supervisors and all other licence classes.
A9: Est. share that are 'builder' class (run whole projects, not trade-only) | B9: 0.08 | F9: ASSUMPTION — QBCC does not publish a public breakdown of licensee counts by class. This is a directional estimate and the single biggest uncertainty in the whole model; worth replacing with the real number from a QBCC data request or the Open Data Portal CSV before relying on this.
A10: Estimated TAM — Qld builder-class businesses | B10: =B8*B9 -> 9760
A11: Serviceable share (small-to-mid builders, 1–30 staff) | B11: 0.6 | F11: ASSUMPTION — excludes sole-operator renovators unlikely to pay for PM software, and large commercial/tier-1 builders who already run enterprise ERP systems.
A12: SAM — Qld serviceable addressable market (businesses) | B12: =B10*B11 -> 5856
A13: Note: expanding beyond Qld (NSW/Vic/etc.) could multiply TAM ~4–5x, but is out of scope for this 5-year model — treat as later upside, not a plan assumption.
A15: CHURN ASSUMPTIONS (monthly, by year)
B16: Year 1 | C16: Year 2 | D16: Year 3 | E16: Year 4 | F16: Year 5
A17: Solo — monthly churn | B17: 0.045 | C17: 0.038 | D17: 0.032 | E17: 0.028 | F17: 0.025
A18: Team — monthly churn | B18: 0.045 | C18: 0.03 | D18: 0.022 | E18: 0.018 | F18: 0.015
A19: Benchmark: SMB SaaS runs 3–5%/mo churn industry-wide; niche vertical tools with high switching cost (a builder's live project data) typically retain better than generic SMB software over time. Team scenario assumes a dedicated customer-success hire pulls churn down faster. Sources: withorb.com/blog/saas-benchmarks (2025), optif.ai churn benchmark report.
A21: NEW CUSTOMER ADDS PACE (customers/month — start of year → end of year, straight-line within year)
B22: Year 1 | C22: Year 2 | D22: Year 3 | E22: Year 4 | F22: Year 5
A23: Solo — pace at start of year | B23: 1 | C23: 5 | D23: 9 | E23: 12 | F23: 15
A24: Solo — pace at end of year | B24: 5 | C24: 9 | D24: 13 | E24: 16 | F24: 18
A25: Team — pace at start of year | B25: 1 | C25: 6 | D25: 14 | E25: 22 | F25: 30
A26: Team — pace at end of year | B26: 5 | C26: 14 | D26: 24 | E26: 32 | F26: 40
A27: ASSUMPTION — an illustrative growth ramp, not a pipeline forecast. Year 1 is identical for both scenarios (no team yet); from Year 2, Team scenario grows faster because a dedicated hire removes the founder as the bottleneck on sales + onboarding + support. Replace with real numbers once you have actual leads/signups to anchor on.
A29: COST ASSUMPTIONS
A30: Infra COGS per customer (per month) | B30: 20 | F30: ASSUMPTION — blended Supabase + Vercel + Anthropic Claude API cost at moderate usage (a few AI document-filing calls per customer per week, plus hosting/storage). Order-of-magnitude estimate; validate against real usage after launch.
B31: Year 1 | C31: Year 2 | D31: Year 3 | E31: Year 4 | F31: Year 5
A32: Solo — marketing & tools spend (per month) | B32: 50 | C32: 120 | D32: 200 | E32: 300 | F32: 400
A33: Team — marketing & tools spend (per month) | B33: 150 | C33: 500 | D33: 1000 | E33: 1500 | F33: 2000
A34: Solo — salaries (n/a, founder-operated) | B34: 0 | C34: 0 | D34: 0 | E34: 0 | F34: 0
A35: Team — salaries, annualized ($/yr, phased hiring) | B35: 0 | C35: 50000 | D35: 130000 | E35: 170000 | F35: 220000
A36: ASSUMPTION — Team scenario phases in: Year 2 part-time customer success hire (~$50k/yr average), Year 3 adds a junior BD/sales hire (~$130k/yr combined), scaling to ~$220k/yr combined by Year 5. Solo scenario has no payroll; Net Income there is pre-tax income available to the founder.
A38: LAUNCH
A39: Model launch (Month 1) | B39: Aug 2026 | F39: Today's date is 19 Jul 2026; the model assumes first paying customers start Aug 2026.

Sheet Solo - Monthly Model
A1: CivFlow — Monthly Model: Solo (founder-operated)
A3: Month # | C3: 1 | D3: 2 | E3: 3 | F3: 4 | G3: 5 | H3: 6 | I3: 7 | J3: 8 | K3: 9 | L3: 10 | M3: 11 | N3: 12 | O3: 13 | P3: 14 | Q3: 15 | R3: 16 | S3: 17 | T3: 18 | U3: 19 | V3: 20 | W3: 21 | X3: 22 | Y3: 23 | Z3: 24 | AA3: 25 | AB3: 26 | AC3: 27 | AD3: 28 | AE3: 29 | AF3: 30 | AG3: 31 | AH3: 32 | AI3: 33 | AJ3: 34 | AK3: 35 | AL3: 36 | AM3: 37 | AN3: 38 | AO3: 39 | AP3: 40 | AQ3: 41 | AR3: 42 | AS3: 43 | AT3: 44 | AU3: 45 | AV3: 46 | AW3: 47 | AX3: 48 | AY3: 49 | AZ3: 50 | BA3: 51 | BB3: 52 | BC3: 53 | BD3: 54 | BE3: 55 | BF3: 56 | BG3: 57 | BH3: 58 | BI3: 59 | BJ3: 60
A4: Calendar month | C4: Aug-26 | D4: Sep-26 | E4: Oct-26 | F4: Nov-26 | G4: Dec-26 | H4: Jan-27 | I4: Feb-27 | J4: Mar-27 | K4: Apr-27 | L4: May-27 | M4: Jun-27 | N4: Jul-27 | O4: Aug-27 | P4: Sep-27 | Q4: Oct-27 | R4: Nov-27 | S4: Dec-27 | T4: Jan-28 | U4: Feb-28 | V4: Mar-28 | W4: Apr-28 | X4: May-28 | Y4: Jun-28 | Z4: Jul-28 | AA4: Aug-28 | AB4: Sep-28 | AC4: Oct-28 | AD4: Nov-28 | AE4: Dec-28 | AF4: Jan-29 | AG4: Feb-29 | AH4: Mar-29 | AI4: Apr-29 | AJ4: May-29 | AK4: Jun-29 | AL4: Jul-29 | AM4: Aug-29 | AN4: Sep-29 | AO4: Oct-29 | AP4: Nov-29 | AQ4: Dec-29 | AR4: Jan-30 | AS4: Feb-30 | AT4: Mar-30 | AU4: Apr-30 | AV4: May-30 | AW4: Jun-30 | AX4: Jul-30 | AY4: Aug-30 | AZ4: Sep-30 | BA4: Oct-30 | BB4: Nov-30 | BC4: Dec-30 | BD4: Jan-31 | BE4: Feb-31 | BF4: Mar-31 | BG4: Apr-31 | BH4: May-31 | BI4: Jun-31 | BJ4: Jul-31
A5: Year | C5: =ROUNDUP(C3/12,0) -> 1 | D5: =ROUNDUP(D3/12,0) -> 1 | E5: =ROUNDUP(E3/12,0) -> 1 | F5: =ROUNDUP(F3/12,0) -> 1 | G5: =ROUNDUP(G3/12,0) -> 1 | H5: =ROUNDUP(H3/12,0) -> 1 | I5: =ROUNDUP(I3/12,0) -> 1 | J5: =ROUNDUP(J3/12,0) -> 1 | ... BJ5: =ROUNDUP(BJ3/12,0) -> 5
A6: Month-in-year | C6: =C3-(C5-1)*12 -> 1 | D6: =D3-(D5-1)*12 -> 2 | E6: =E3-(E5-1)*12 -> 3 | F6: =F3-(F5-1)*12 -> 4 | G6: =G3-(G5-1)*12 -> 5 | H6: =H3-(H5-1)*12 -> 6 | I6: =I3-(I5-1)*12 -> 7 | J6: =J3-(J5-1)*12 -> 8 | ... BJ6: =BJ3-(BJ5-1)*12 -> 12
A8: New customers added | C8: =ROUND(INDEX(Assumptions!$B$23:$F$23,1,C5)+(INDEX(Assumptions!$B$24:$F$24,1,C5)-INDEX(Assumptions!$B$23:$F$23,1,C5))*(C6-1)/11,1) -> 1 | D8: =ROUND(INDEX(Assumptions!$B$23:$F$23,1,D5)+(INDEX(Assumptions!$B$24:$F$24,1,D5)-INDEX(Assumptions!$B$23:$F$23,1,D5))*(D6-1)/11,1) -> 1.4 | E8: =ROUND(INDEX(Assumptions!$B$23:$F$23,1,E5)+(INDEX(Assumptions!$B$24:$F$24,1,E5)-INDEX(Assumptions!$B$23:$F$23,1,E5))*(E6-1)/11,1) -> 1.7 | F8: =ROUND(INDEX(Assumptions!$B$23:$F$23,1,F5)+(INDEX(Assumptions!$B$24:$F$24,1,F5)-INDEX(Assumptions!$B$23:$F$23,1,F5))*(F6-1)/11,1) -> 2.1 | G8: =ROUND(INDEX(Assumptions!$B$23:$F$23,1,G5)+(INDEX(Assumptions!$B$24:$F$24,1,G5)-INDEX(Assumptions!$B$23:$F$23,1,G5))*(G6-1)/11,1) -> 2.5 | H8: =ROUND(INDEX(Assumptions!$B$23:$F$23,1,H5)+(INDEX(Assumptions!$B$24:$F$24,1,H5)-INDEX(Assumptions!$B$23:$F$23,1,H5))*(H6-1)/11,1) -> 2.8 | I8: =ROUND(INDEX(Assumptions!$B$23:$F$23,1,I5)+(INDEX(Assumptions!$B$24:$F$24,1,I5)-INDEX(Assumptions!$B$23:$F$23,1,I5))*(I6-1)/11,1) -> 3.2 | J8: =ROUND(INDEX(Assumptions!$B$23:$F$23,1,J5)+(INDEX(Assumptions!$B$24:$F$24,1,J5)-INDEX(Assumptions!$B$23:$F$23,1,J5))*(J6-1)/11,1) -> 3.5 | ... BJ8: =ROUND(INDEX(Assumptions!$B$23:$F$23,1,BJ5)+(INDEX(Assumptions!$B$24:$F$24,1,BJ5)-INDEX(Assumptions!$B$23:$F$23,1,BJ5))*(BJ6-1)/11,1) -> 18
A9: Monthly churn rate | C9: =INDEX(Assumptions!$B$17:$F$17,1,C5) -> 0.045 | D9: =INDEX(Assumptions!$B$17:$F$17,1,D5) -> 0.045 | E9: =INDEX(Assumptions!$B$17:$F$17,1,E5) -> 0.045 | F9: =INDEX(Assumptions!$B$17:$F$17,1,F5) -> 0.045 | G9: =INDEX(Assumptions!$B$17:$F$17,1,G5) -> 0.045 | H9: =INDEX(Assumptions!$B$17:$F$17,1,H5) -> 0.045 | I9: =INDEX(Assumptions!$B$17:$F$17,1,I5) -> 0.045 | J9: =INDEX(Assumptions!$B$17:$F$17,1,J5) -> 0.045 | ... BJ9: =INDEX(Assumptions!$B$17:$F$17,1,BJ5) -> 0.025
A10: Customers churned | C10: =0 -> 0 | D10: =C11*D9 -> 0.045 | E10: =D11*E9 -> 0.105975 | F10: =E11*F9 -> 0.17770612 | G10: =F11*G9 -> 0.26420935 | H10: =G11*H9 -> 0.36481993 | I10: =H11*I9 -> 0.47440303 | J10: =I11*J9 -> 0.5970549 | K10: =J11*K9 -> 0.72768743 | ... BJ10: =BI11*BJ9 -> 9.0759354
A11: Ending customers | C11: =C8-C10 -> 1 | D11: =C11+D8-D10 -> 2.355 | E11: =D11+E8-E10 -> 3.949025 | F11: =E11+F8-F10 -> 5.8713189 | G11: =F11+G8-G10 -> 8.1071095 | H11: =G11+H8-H10 -> 10.54229 | I11: =H11+I8-I10 -> 13.267887 | J11: =I11+J8-J10 -> 16.170832 | K11: =J11+K8-K10 -> 19.343144 | ... BJ11: =BI11+BJ8-BJ10 -> 371.96148
A13: MRR | C13: =C11*Assumptions!$B$5 -> 200 | D13: =D11*Assumptions!$B$5 -> 471 | E13: =E11*Assumptions!$B$5 -> 789.805 | F13: =F11*Assumptions!$B$5 -> 1174.2638 | G13: =G11*Assumptions!$B$5 -> 1621.4219 | H13: =H11*Assumptions!$B$5 -> 2108.4579 | I13: =I11*Assumptions!$B$5 -> 2653.5773 | J13: =J11*Assumptions!$B$5 -> 3234.1663 | ... BJ13: =BJ11*Assumptions!$B$5 -> 74392.296
A14: ARR (run-rate) | C14: =C13*12 -> 2400 | D14: =D13*12 -> 5652 | E14: =E13*12 -> 9477.66 | F14: =F13*12 -> 14091.165 | G14: =G13*12 -> 19457.063 | H14: =H13*12 -> 25301.495 | I14: =I13*12 -> 31842.928 | J14: =J13*12 -> 38809.996 | ... BJ14: =BJ13*12 -> 892707.56
A16: Infra COGS | C16: =C11*Assumptions!$B$30 -> 20 | D16: =D11*Assumptions!$B$30 -> 47.1 | E16: =E11*Assumptions!$B$30 -> 78.9805 | F16: =F11*Assumptions!$B$30 -> 117.42638 | G16: =G11*Assumptions!$B$30 -> 162.14219 | H16: =H11*Assumptions!$B$30 -> 210.84579 | I16: =I11*Assumptions!$B$30 -> 265.35773 | J16: =J11*Assumptions!$B$30 -> 323.41663 | ... BJ16: =BJ11*Assumptions!$B$30 -> 7439.2296
A17: Gross profit | C17: =C13-C16 -> 180 | D17: =D13-D16 -> 423.9 | E17: =E13-E16 -> 710.8245 | F17: =F13-F16 -> 1056.8374 | G17: =G13-G16 -> 1459.2797 | H17: =H13-H16 -> 1897.6121 | I17: =I13-I16 -> 2388.2196 | J17: =J13-J16 -> 2910.7497 | ... BJ17: =BJ13-BJ16 -> 66953.067
A18: Gross margin % | C18: =IFERROR(C17/C13,0) -> 0.9 | D18: =IFERROR(D17/D13,0) -> 0.9 | E18: =IFERROR(E17/E13,0) -> 0.9 | F18: =IFERROR(F17/F13,0) -> 0.9 | G18: =IFERROR(G17/G13,0) -> 0.9 | H18: =IFERROR(H17/H13,0) -> 0.9 | I18: =IFERROR(I17/I13,0) -> 0.9 | J18: =IFERROR(J17/J13,0) -> 0.9 | ... BJ18: =IFERROR(BJ17/BJ13,0) -> 0.9
A20: Marketing & tools spend | C20: =INDEX(Assumptions!$B$32:$F$32,1,C5) -> 50 | D20: =INDEX(Assumptions!$B$32:$F$32,1,D5) -> 50 | E20: =INDEX(Assumptions!$B$32:$F$32,1,E5) -> 50 | F20: =INDEX(Assumptions!$B$32:$F$32,1,F5) -> 50 | G20: =INDEX(Assumptions!$B$32:$F$32,1,G5) -> 50 | H20: =INDEX(Assumptions!$B$32:$F$32,1,H5) -> 50 | I20: =INDEX(Assumptions!$B$32:$F$32,1,I5) -> 50 | J20: =INDEX(Assumptions!$B$32:$F$32,1,J5) -> 50 | ... BJ20: =INDEX(Assumptions!$B$32:$F$32,1,BJ5) -> 400
A21: Salaries | C21: =INDEX(Assumptions!$B$34:$F$34,1,C5)/12 -> 0 | D21: =INDEX(Assumptions!$B$34:$F$34,1,D5)/12 -> 0 | E21: =INDEX(Assumptions!$B$34:$F$34,1,E5)/12 -> 0 | F21: =INDEX(Assumptions!$B$34:$F$34,1,F5)/12 -> 0 | G21: =INDEX(Assumptions!$B$34:$F$34,1,G5)/12 -> 0 | H21: =INDEX(Assumptions!$B$34:$F$34,1,H5)/12 -> 0 | I21: =INDEX(Assumptions!$B$34:$F$34,1,I5)/12 -> 0 | J21: =INDEX(Assumptions!$B$34:$F$34,1,J5)/12 -> 0 | ... BJ21: =INDEX(Assumptions!$B$34:$F$34,1,BJ5)/12 -> 0
A22: Total opex (below gross profit) | C22: =C20+C21 -> 50 | D22: =D20+D21 -> 50 | E22: =E20+E21 -> 50 | F22: =F20+F21 -> 50 | G22: =G20+G21 -> 50 | H22: =H20+H21 -> 50 | I22: =I20+I21 -> 50 | J22: =J20+J21 -> 50 | ... BJ22: =BJ20+BJ21 -> 400
A24: Net income (monthly) | C24: =C17-C22 -> 130 | D24: =D17-D22 -> 373.9 | E24: =E17-E22 -> 660.8245 | F24: =F17-F22 -> 1006.8374 | G24: =G17-G22 -> 1409.2797 | H24: =H17-H22 -> 1847.6121 | I24: =I17-I22 -> 2338.2196 | J24: =J17-J22 -> 2860.7497 | ... BJ24: =BJ17-BJ22 -> 66553.067
A25: Cumulative net cash flow | C25: =C24 -> 130 | D25: =C25+D24 -> 503.9 | E25: =D25+E24 -> 1164.7245 | F25: =E25+F24 -> 2171.5619 | G25: =F25+G24 -> 3580.8416 | H25: =G25+H24 -> 5428.4537 | I25: =H25+I24 -> 7766.6733 | J25: =I25+J24 -> 10627.423 | K25: =J25+K24 -> 14059.189 | ... BJ25: =BI25+BJ24 -> 1613302
A27: Net income positive? (1/0) | C27: =IF(C24>0,1,0) -> 1 | D27: =IF(D24>0,1,0) -> 1 | E27: =IF(E24>0,1,0) -> 1 | F27: =IF(F24>0,1,0) -> 1 | G27: =IF(G24>0,1,0) -> 1 | H27: =IF(H24>0,1,0) -> 1 | I27: =IF(I24>0,1,0) -> 1 | J27: =IF(J24>0,1,0) -> 1 | ... BJ27: =IF(BJ24>0,1,0) -> 1

Sheet Team - Monthly Model
A1: CivFlow — Monthly Model: Small Team (phased hiring from Year 2)
A3: Month # | C3: 1 | D3: 2 | E3: 3 | F3: 4 | G3: 5 | H3: 6 | I3: 7 | J3: 8 | K3: 9 | L3: 10 | M3: 11 | N3: 12 | O3: 13 | P3: 14 | Q3: 15 | R3: 16 | S3: 17 | T3: 18 | U3: 19 | V3: 20 | W3: 21 | X3: 22 | Y3: 23 | Z3: 24 | AA3: 25 | AB3: 26 | AC3: 27 | AD3: 28 | AE3: 29 | AF3: 30 | AG3: 31 | AH3: 32 | AI3: 33 | AJ3: 34 | AK3: 35 | AL3: 36 | AM3: 37 | AN3: 38 | AO3: 39 | AP3: 40 | AQ3: 41 | AR3: 42 | AS3: 43 | AT3: 44 | AU3: 45 | AV3: 46 | AW3: 47 | AX3: 48 | AY3: 49 | AZ3: 50 | BA3: 51 | BB3: 52 | BC3: 53 | BD3: 54 | BE3: 55 | BF3: 56 | BG3: 57 | BH3: 58 | BI3: 59 | BJ3: 60
A4: Calendar month | C4: Aug-26 | D4: Sep-26 | E4: Oct-26 | F4: Nov-26 | G4: Dec-26 | H4: Jan-27 | I4: Feb-27 | J4: Mar-27 | K4: Apr-27 | L4: May-27 | M4: Jun-27 | N4: Jul-27 | O4: Aug-27 | P4: Sep-27 | Q4: Oct-27 | R4: Nov-27 | S4: Dec-27 | T4: Jan-28 | U4: Feb-28 | V4: Mar-28 | W4: Apr-28 | X4: May-28 | Y4: Jun-28 | Z4: Jul-28 | AA4: Aug-28 | AB4: Sep-28 | AC4: Oct-28 | AD4: Nov-28 | AE4: Dec-28 | AF4: Jan-29 | AG4: Feb-29 | AH4: Mar-29 | AI4: Apr-29 | AJ4: May-29 | AK4: Jun-29 | AL4: Jul-29 | AM4: Aug-29 | AN4: Sep-29 | AO4: Oct-29 | AP4: Nov-29 | AQ4: Dec-29 | AR4: Jan-30 | AS4: Feb-30 | AT4: Mar-30 | AU4: Apr-30 | AV4: May-30 | AW4: Jun-30 | AX4: Jul-30 | AY4: Aug-30 | AZ4: Sep-30 | BA4: Oct-30 | BB4: Nov-30 | BC4: Dec-30 | BD4: Jan-31 | BE4: Feb-31 | BF4: Mar-31 | BG4: Apr-31 | BH4: May-31 | BI4: Jun-31 | BJ4: Jul-31
A5: Year | C5: =ROUNDUP(C3/12,0) -> 1 | D5: =ROUNDUP(D3/12,0) -> 1 | E5: =ROUNDUP(E3/12,0) -> 1 | F5: =ROUNDUP(F3/12,0) -> 1 | G5: =ROUNDUP(G3/12,0) -> 1 | H5: =ROUNDUP(H3/12,0) -> 1 | I5: =ROUNDUP(I3/12,0) -> 1 | J5: =ROUNDUP(J3/12,0) -> 1 | ... BJ5: =ROUNDUP(BJ3/12,0) -> 5
A6: Month-in-year | C6: =C3-(C5-1)*12 -> 1 | D6: =D3-(D5-1)*12 -> 2 | E6: =E3-(E5-1)*12 -> 3 | F6: =F3-(F5-1)*12 -> 4 | G6: =G3-(G5-1)*12 -> 5 | H6: =H3-(H5-1)*12 -> 6 | I6: =I3-(I5-1)*12 -> 7 | J6: =J3-(J5-1)*12 -> 8 | ... BJ6: =BJ3-(BJ5-1)*12 -> 12
A8: New customers added | C8: =ROUND(INDEX(Assumptions!$B$25:$F$25,1,C5)+(INDEX(Assumptions!$B$26:$F$26,1,C5)-INDEX(Assumptions!$B$25:$F$25,1,C5))*(C6-1)/11,1) -> 1 | D8: =ROUND(INDEX(Assumptions!$B$25:$F$25,1,D5)+(INDEX(Assumptions!$B$26:$F$26,1,D5)-INDEX(Assumptions!$B$25:$F$25,1,D5))*(D6-1)/11,1) -> 1.4 | E8: =ROUND(INDEX(Assumptions!$B$25:$F$25,1,E5)+(INDEX(Assumptions!$B$26:$F$26,1,E5)-INDEX(Assumptions!$B$25:$F$25,1,E5))*(E6-1)/11,1) -> 1.7 | F8: =ROUND(INDEX(Assumptions!$B$25:$F$25,1,F5)+(INDEX(Assumptions!$B$26:$F$26,1,F5)-INDEX(Assumptions!$B$25:$F$25,1,F5))*(F6-1)/11,1) -> 2.1 | G8: =ROUND(INDEX(Assumptions!$B$25:$F$25,1,G5)+(INDEX(Assumptions!$B$26:$F$26,1,G5)-INDEX(Assumptions!$B$25:$F$25,1,G5))*(G6-1)/11,1) -> 2.5 | H8: =ROUND(INDEX(Assumptions!$B$25:$F$25,1,H5)+(INDEX(Assumptions!$B$26:$F$26,1,H5)-INDEX(Assumptions!$B$25:$F$25,1,H5))*(H6-1)/11,1) -> 2.8 | I8: =ROUND(INDEX(Assumptions!$B$25:$F$25,1,I5)+(INDEX(Assumptions!$B$26:$F$26,1,I5)-INDEX(Assumptions!$B$25:$F$25,1,I5))*(I6-1)/11,1) -> 3.2 | J8: =ROUND(INDEX(Assumptions!$B$25:$F$25,1,J5)+(INDEX(Assumptions!$B$26:$F$26,1,J5)-INDEX(Assumptions!$B$25:$F$25,1,J5))*(J6-1)/11,1) -> 3.5 | ... BJ8: =ROUND(INDEX(Assumptions!$B$25:$F$25,1,BJ5)+(INDEX(Assumptions!$B$26:$F$26,1,BJ5)-INDEX(Assumptions!$B$25:$F$25,1,BJ5))*(BJ6-1)/11,1) -> 40
A9: Monthly churn rate | C9: =INDEX(Assumptions!$B$18:$F$18,1,C5) -> 0.045 | D9: =INDEX(Assumptions!$B$18:$F$18,1,D5) -> 0.045 | E9: =INDEX(Assumptions!$B$18:$F$18,1,E5) -> 0.045 | F9: =INDEX(Assumptions!$B$18:$F$18,1,F5) -> 0.045 | G9: =INDEX(Assumptions!$B$18:$F$18,1,G5) -> 0.045 | H9: =INDEX(Assumptions!$B$18:$F$18,1,H5) -> 0.045 | I9: =INDEX(Assumptions!$B$18:$F$18,1,I5) -> 0.045 | J9: =INDEX(Assumptions!$B$18:$F$18,1,J5) -> 0.045 | ... BJ9: =INDEX(Assumptions!$B$18:$F$18,1,BJ5) -> 0.015
A10: Customers churned | C10: =0 -> 0 | D10: =C11*D9 -> 0.045 | E10: =D11*E9 -> 0.105975 | F10: =E11*F9 -> 0.17770612 | G10: =F11*G9 -> 0.26420935 | H10: =G11*H9 -> 0.36481993 | I10: =H11*I9 -> 0.47440303 | J10: =I11*J9 -> 0.5970549 | K10: =J11*K9 -> 0.72768743 | ... BJ10: =BI11*BJ9 -> 12.147271
A11: Ending customers | C11: =C8-C10 -> 1 | D11: =C11+D8-D10 -> 2.355 | E11: =D11+E8-E10 -> 3.949025 | F11: =E11+F8-F10 -> 5.8713189 | G11: =F11+G8-G10 -> 8.1071095 | H11: =G11+H8-H10 -> 10.54229 | I11: =H11+I8-I10 -> 13.267887 | J11: =I11+J8-J10 -> 16.170832 | K11: =J11+K8-K10 -> 19.343144 | ... BJ11: =BI11+BJ8-BJ10 -> 837.67078
A13: MRR | C13: =C11*Assumptions!$B$5 -> 200 | D13: =D11*Assumptions!$B$5 -> 471 | E13: =E11*Assumptions!$B$5 -> 789.805 | F13: =F11*Assumptions!$B$5 -> 1174.2638 | G13: =G11*Assumptions!$B$5 -> 1621.4219 | H13: =H11*Assumptions!$B$5 -> 2108.4579 | I13: =I11*Assumptions!$B$5 -> 2653.5773 | J13: =J11*Assumptions!$B$5 -> 3234.1663 | ... BJ13: =BJ11*Assumptions!$B$5 -> 167534.16
A14: ARR (run-rate) | C14: =C13*12 -> 2400 | D14: =D13*12 -> 5652 | E14: =E13*12 -> 9477.66 | F14: =F13*12 -> 14091.165 | G14: =G13*12 -> 19457.063 | H14: =H13*12 -> 25301.495 | I14: =I13*12 -> 31842.928 | J14: =J13*12 -> 38809.996 | ... BJ14: =BJ13*12 -> 2010409.9
A16: Infra COGS | C16: =C11*Assumptions!$B$30 -> 20 | D16: =D11*Assumptions!$B$30 -> 47.1 | E16: =E11*Assumptions!$B$30 -> 78.9805 | F16: =F11*Assumptions!$B$30 -> 117.42638 | G16: =G11*Assumptions!$B$30 -> 162.14219 | H16: =H11*Assumptions!$B$30 -> 210.84579 | I16: =I11*Assumptions!$B$30 -> 265.35773 | J16: =J11*Assumptions!$B$30 -> 323.41663 | ... BJ16: =BJ11*Assumptions!$B$30 -> 16753.416
A17: Gross profit | C17: =C13-C16 -> 180 | D17: =D13-D16 -> 423.9 | E17: =E13-E16 -> 710.8245 | F17: =F13-F16 -> 1056.8374 | G17: =G13-G16 -> 1459.2797 | H17: =H13-H16 -> 1897.6121 | I17: =I13-I16 -> 2388.2196 | J17: =J13-J16 -> 2910.7497 | ... BJ17: =BJ13-BJ16 -> 150780.74
A18: Gross margin % | C18: =IFERROR(C17/C13,0) -> 0.9 | D18: =IFERROR(D17/D13,0) -> 0.9 | E18: =IFERROR(E17/E13,0) -> 0.9 | F18: =IFERROR(F17/F13,0) -> 0.9 | G18: =IFERROR(G17/G13,0) -> 0.9 | H18: =IFERROR(H17/H13,0) -> 0.9 | I18: =IFERROR(I17/I13,0) -> 0.9 | J18: =IFERROR(J17/J13,0) -> 0.9 | ... BJ18: =IFERROR(BJ17/BJ13,0) -> 0.9
A20: Marketing & tools spend | C20: =INDEX(Assumptions!$B$33:$F$33,1,C5) -> 150 | D20: =INDEX(Assumptions!$B$33:$F$33,1,D5) -> 150 | E20: =INDEX(Assumptions!$B$33:$F$33,1,E5) -> 150 | F20: =INDEX(Assumptions!$B$33:$F$33,1,F5) -> 150 | G20: =INDEX(Assumptions!$B$33:$F$33,1,G5) -> 150 | H20: =INDEX(Assumptions!$B$33:$F$33,1,H5) -> 150 | I20: =INDEX(Assumptions!$B$33:$F$33,1,I5) -> 150 | J20: =INDEX(Assumptions!$B$33:$F$33,1,J5) -> 150 | ... BJ20: =INDEX(Assumptions!$B$33:$F$33,1,BJ5) -> 2000
A21: Salaries | C21: =INDEX(Assumptions!$B$35:$F$35,1,C5)/12 -> 0 | D21: =INDEX(Assumptions!$B$35:$F$35,1,D5)/12 -> 0 | E21: =INDEX(Assumptions!$B$35:$F$35,1,E5)/12 -> 0 | F21: =INDEX(Assumptions!$B$35:$F$35,1,F5)/12 -> 0 | G21: =INDEX(Assumptions!$B$35:$F$35,1,G5)/12 -> 0 | H21: =INDEX(Assumptions!$B$35:$F$35,1,H5)/12 -> 0 | I21: =INDEX(Assumptions!$B$35:$F$35,1,I5)/12 -> 0 | J21: =INDEX(Assumptions!$B$35:$F$35,1,J5)/12 -> 0 | ... BJ21: =INDEX(Assumptions!$B$35:$F$35,1,BJ5)/12 -> 18333.333
A22: Total opex (below gross profit) | C22: =C20+C21 -> 150 | D22: =D20+D21 -> 150 | E22: =E20+E21 -> 150 | F22: =F20+F21 -> 150 | G22: =G20+G21 -> 150 | H22: =H20+H21 -> 150 | I22: =I20+I21 -> 150 | J22: =J20+J21 -> 150 | ... BJ22: =BJ20+BJ21 -> 20333.333
A24: Net income (monthly) | C24: =C17-C22 -> 30 | D24: =D17-D22 -> 273.9 | E24: =E17-E22 -> 560.8245 | F24: =F17-F22 -> 906.8374 | G24: =G17-G22 -> 1309.2797 | H24: =H17-H22 -> 1747.6121 | I24: =I17-I22 -> 2238.2196 | J24: =J17-J22 -> 2760.7497 | ... BJ24: =BJ17-BJ22 -> 130447.41
A25: Cumulative net cash flow | C25: =C24 -> 30 | D25: =C25+D24 -> 303.9 | E25: =D25+E24 -> 864.7245 | F25: =E25+F24 -> 1771.5619 | G25: =F25+G24 -> 3080.8416 | H25: =G25+H24 -> 4828.4537 | I25: =H25+I24 -> 7066.6733 | J25: =I25+J24 -> 9827.423 | K25: =J25+K24 -> 13159.189 | ... BJ25: =BI25+BJ24 -> 2434567.7
A27: Net income positive? (1/0) | C27: =IF(C24>0,1,0) -> 1 | D27: =IF(D24>0,1,0) -> 1 | E27: =IF(E24>0,1,0) -> 1 | F27: =IF(F24>0,1,0) -> 1 | G27: =IF(G24>0,1,0) -> 1 | H27: =IF(H24>0,1,0) -> 1 | I27: =IF(I24>0,1,0) -> 1 | J27: =IF(J24>0,1,0) -> 1 | ... BJ27: =IF(BJ24>0,1,0) -> 1

Sheet Annual Summary & Milestones
A1: CivFlow — 5-Year Annual Summary & Milestones
A2: Year-end snapshots pulled from the monthly models. Solo = founder-operated. Team = phased hiring from Year 2. All figures AUD.
B4: SOLO SCENARIO | H4: TEAM SCENARIO
B5: Year 1 | C5: Year 2 | D5: Year 3 | E5: Year 4 | F5: Year 5 | H5: Year 1 | I5: Year 2 | J5: Year 3 | K5: Year 4 | L5: Year 5
A6: Ending customers (year-end) | B6: ='Solo - Monthly Model'!N11 -> 30.162274 | C6: ='Solo - Monthly Model'!Z11 -> 89.063928 | D6: ='Solo - Monthly Model'!AL11 -> 172.77235 | E6: ='Solo - Monthly Model'!AX11 -> 268.53338 | F6: ='Solo - Monthly Model'!BJ11 -> 371.96148 | H6: ='Team - Monthly Model'!N11 -> 30.162274 | I6: ='Team - Monthly Model'!Z11 -> 125.6658 | J6: ='Team - Monthly Model'!AL11 -> 301.13562 | K6: ='Team - Monthly Model'!AX11 -> 538.079 | L6: ='Team - Monthly Model'!BJ11 -> 837.67078
A7: New customers added (annual) | B7: =SUM('Solo - Monthly Model'!C8:N8) -> 36 | C7: =SUM('Solo - Monthly Model'!O8:Z8) -> 84 | D7: =SUM('Solo - Monthly Model'!AA8:AL8) -> 132 | E7: =SUM('Solo - Monthly Model'!AM8:AX8) -> 168 | F7: =SUM('Solo - Monthly Model'!AY8:BJ8) -> 198 | H7: =SUM('Team - Monthly Model'!C8:N8) -> 36 | I7: =SUM('Team - Monthly Model'!O8:Z8) -> 120 | J7: =SUM('Team - Monthly Model'!AA8:AL8) -> 228 | K7: =SUM('Team - Monthly Model'!AM8:AX8) -> 324 | L7: =SUM('Team - Monthly Model'!AY8:BJ8) -> 420
A8: Customers churned (annual) | B8: =SUM('Solo - Monthly Model'!C10:N10) -> 5.8377258 | C8: =SUM('Solo - Monthly Model'!O10:Z10) -> 25.098346 | D8: =SUM('Solo - Monthly Model'!AA10:AL10) -> 48.291578 | E8: =SUM('Solo - Monthly Model'!AM10:AX10) -> 72.238968 | F8: =SUM('Solo - Monthly Model'!AY10:BJ10) -> 94.5719 | H8: =SUM('Team - Monthly Model'!C10:N10) -> 5.8377258 | I8: =SUM('Team - Monthly Model'!O10:Z10) -> 24.496478 | J8: =SUM('Team - Monthly Model'!AA10:AL10) -> 52.530173 | K8: =SUM('Team - Monthly Model'!AM10:AX10) -> 87.056622 | L8: =SUM('Team - Monthly Model'!AY10:BJ10) -> 120.40822
A9: MRR (year-end) | B9: ='Solo - Monthly Model'!N13 -> 6032.4548 | C9: ='Solo - Monthly Model'!Z13 -> 17812.786 | D9: ='Solo - Monthly Model'!AL13 -> 34554.47 | E9: ='Solo - Monthly Model'!AX13 -> 53706.676 | F9: ='Solo - Monthly Model'!BJ13 -> 74392.296 | H9: ='Team - Monthly Model'!N13 -> 6032.4548 | I9: ='Team - Monthly Model'!Z13 -> 25133.159 | J9: ='Team - Monthly Model'!AL13 -> 60227.125 | K9: ='Team - Monthly Model'!AX13 -> 107615.8 | L9: ='Team - Monthly Model'!BJ13 -> 167534.16
A10: ARR (year-end run-rate) | B10: ='Solo - Monthly Model'!N14 -> 72389.458 | C10: ='Solo - Monthly Model'!Z14 -> 213753.43 | D10: ='Solo - Monthly Model'!AL14 -> 414653.64 | E10: ='Solo - Monthly Model'!AX14 -> 644480.12 | F10: ='Solo - Monthly Model'!BJ14 -> 892707.56 | H10: ='Team - Monthly Model'!N14 -> 72389.458 | I10: ='Team - Monthly Model'!Z14 -> 301597.91 | J10: ='Team - Monthly Model'!AL14 -> 722725.5 | K10: ='Team - Monthly Model'!AX14 -> 1291389.6 | L10: ='Team - Monthly Model'!BJ14 -> 2010409.9
A11: Annual revenue (actual, sum of monthly MRR) | B11: =SUM('Solo - Monthly Model'!C13:N13) -> 31977.903 | C11: =SUM('Solo - Monthly Model'!O13:Z13) -> 143876.89 | D11: =SUM('Solo - Monthly Model'!AA13:AL13) -> 318564.05 | E11: =SUM('Solo - Monthly Model'!AM13:AX13) -> 535144.83 | F11: =SUM('Solo - Monthly Model'!AY13:BJ13) -> 777260.82 | H11: =SUM('Team - Monthly Model'!C13:N13) -> 31977.903 | I11: =SUM('Team - Monthly Model'!O13:Z13) -> 182410.56 | J11: =SUM('Team - Monthly Model'!AA13:AL13) -> 512640.99 | K11: =SUM('Team - Monthly Model'!AM13:AX13) -> 1014684.5 | L11: =SUM('Team - Monthly Model'!AY13:BJ13) -> 1665361.3 | N11: Actual billed revenue for the year (accounts for ramp within the year) — different from, and lower than, year-end ARR run-rate.
A12: Annual gross profit | B12: =SUM('Solo - Monthly Model'!C17:N17) -> 28780.112 | C12: =SUM('Solo - Monthly Model'!O17:Z17) -> 129489.2 | D12: =SUM('Solo - Monthly Model'!AA17:AL17) -> 286707.64 | E12: =SUM('Solo - Monthly Model'!AM17:AX17) -> 481630.35 | F12: =SUM('Solo - Monthly Model'!AY17:BJ17) -> 699534.74 | H12: =SUM('Team - Monthly Model'!C17:N17) -> 28780.112 | I12: =SUM('Team - Monthly Model'!O17:Z17) -> 164169.5 | J12: =SUM('Team - Monthly Model'!AA17:AL17) -> 461376.89 | K12: =SUM('Team - Monthly Model'!AM17:AX17) -> 913216.03 | L12: =SUM('Team - Monthly Model'!AY17:BJ17) -> 1498825.2
A13: Annual opex (marketing + salaries) | B13: =SUM('Solo - Monthly Model'!C22:N22) -> 600 | C13: =SUM('Solo - Monthly Model'!O22:Z22) -> 1440 | D13: =SUM('Solo - Monthly Model'!AA22:AL22) -> 2400 | E13: =SUM('Solo - Monthly Model'!AM22:AX22) -> 3600 | F13: =SUM('Solo - Monthly Model'!AY22:BJ22) -> 4800 | H13: =SUM('Team - Monthly Model'!C22:N22) -> 1800 | I13: =SUM('Team - Monthly Model'!O22:Z22) -> 56000 | J13: =SUM('Team - Monthly Model'!AA22:AL22) -> 142000 | K13: =SUM('Team - Monthly Model'!AM22:AX22) -> 188000 | L13: =SUM('Team - Monthly Model'!AY22:BJ22) -> 244000
A14: Annual net income | B14: =SUM('Solo - Monthly Model'!C24:N24) -> 28180.112 | C14: =SUM('Solo - Monthly Model'!O24:Z24) -> 128049.2 | D14: =SUM('Solo - Monthly Model'!AA24:AL24) -> 284307.64 | E14: =SUM('Solo - Monthly Model'!AM24:AX24) -> 478030.35 | F14: =SUM('Solo - Monthly Model'!AY24:BJ24) -> 694734.74 | H14: =SUM('Team - Monthly Model'!C24:N24) -> 26980.112 | I14: =SUM('Team - Monthly Model'!O24:Z24) -> 108169.5 | J14: =SUM('Team - Monthly Model'!AA24:AL24) -> 319376.89 | K14: =SUM('Team - Monthly Model'!AM24:AX24) -> 725216.03 | L14: =SUM('Team - Monthly Model'!AY24:BJ24) -> 1254825.2 | N14: Solo: pre-tax income available to the founder (no payroll modeled). Team: pre-tax business profit after salaries.
A15: Cumulative net cash flow (year-end) | B15: ='Solo - Monthly Model'!N25 -> 28180.112 | C15: ='Solo - Monthly Model'!Z25 -> 156229.31 | D15: ='Solo - Monthly Model'!AL25 -> 440536.96 | E15: ='Solo - Monthly Model'!AX25 -> 918567.31 | F15: ='Solo - Monthly Model'!BJ25 -> 1613302 | H15: ='Team - Monthly Model'!N25 -> 26980.112 | I15: ='Team - Monthly Model'!Z25 -> 135149.61 | J15: ='Team - Monthly Model'!AL25 -> 454526.51 | K15: ='Team - Monthly Model'!AX25 -> 1179742.5 | L15: ='Team - Monthly Model'!BJ25 -> 2434567.7
A16: Customers as % of SAM | B16: =IFERROR('Solo - Monthly Model'!N11/Assumptions!$B$12,0) -> 0.0051506616 | C16: =IFERROR('Solo - Monthly Model'!Z11/Assumptions!$B$12,0) -> 0.015209004 | D16: =IFERROR('Solo - Monthly Model'!AL11/Assumptions!$B$12,0) -> 0.029503475 | E16: =IFERROR('Solo - Monthly Model'!AX11/Assumptions!$B$12,0) -> 0.04585611 | F16: =IFERROR('Solo - Monthly Model'!BJ11/Assumptions!$B$12,0) -> 0.063518013 | H16: =IFERROR('Team - Monthly Model'!N11/Assumptions!$B$12,0) -> 0.0051506616 | I16: =IFERROR('Team - Monthly Model'!Z11/Assumptions!$B$12,0) -> 0.021459323 | J16: =IFERROR('Team - Monthly Model'!AL11/Assumptions!$B$12,0) -> 0.051423433 | K16: =IFERROR('Team - Monthly Model'!AX11/Assumptions!$B$12,0) -> 0.091885075 | L16: =IFERROR('Team - Monthly Model'!BJ11/Assumptions!$B$12,0) -> 0.14304487 | N16: Sanity check: share of the ~Qld serviceable market (Assumptions tab) captured by Year 5. Keep this in view — if it looks too high to be credible, the growth ramp assumptions are too aggressive.
A18: MILESTONES — WHAT TO AIM FOR
B19: Solo | C19: Team
A20: First month with 100 customers | B20: =IF(MAX('Solo - Monthly Model'!$C$11:$BJ$11)<100,"Not reached in 5 yrs","Month "&(MATCH(100,'Solo - Monthly Model'!$C$11:$BJ$11,1)+1)&" ("&TEXT(EDATE(DATE(2026,8,1),MATCH(100,'Solo - Monthly Model'!$C$11:$BJ$11,1)),"mmm-yy")&")") -> Month 26 (Sep-28) | C20: =IF(MAX('Team - Monthly Model'!$C$11:$BJ$11)<100,"Not reached in 5 yrs","Month "&(MATCH(100,'Team - Monthly Model'!$C$11:$BJ$11,1)+1)&" ("&TEXT(EDATE(DATE(2026,8,1),MATCH(100,'Team - Monthly Model'!$C$11:$BJ$11,1)),"mmm-yy")&")") -> Month 22 (May-28)
A21: First month MRR reaches $10,000 | B21: =IF(MAX('Solo - Monthly Model'!$C$13:$BJ$13)<10000,"Not reached in 5 yrs","Month "&(MATCH(10000,'Solo - Monthly Model'!$C$13:$BJ$13,1)+1)&" ("&TEXT(EDATE(DATE(2026,8,1),MATCH(10000,'Solo - Monthly Model'!$C$13:$BJ$13,1)),"mmm-yy")&")") -> Month 17 (Dec-27) | C21: =IF(MAX('Team - Monthly Model'!$C$13:$BJ$13)<10000,"Not reached in 5 yrs","Month "&(MATCH(10000,'Team - Monthly Model'!$C$13:$BJ$13,1)+1)&" ("&TEXT(EDATE(DATE(2026,8,1),MATCH(10000,'Team - Monthly Model'!$C$13:$BJ$13,1)),"mmm-yy")&")") -> Month 16 (Nov-27)
A22: First month MRR reaches $50,000 | B22: =IF(MAX('Solo - Monthly Model'!$C$13:$BJ$13)<50000,"Not reached in 5 yrs","Month "&(MATCH(50000,'Solo - Monthly Model'!$C$13:$BJ$13,1)+1)&" ("&TEXT(EDATE(DATE(2026,8,1),MATCH(50000,'Solo - Monthly Model'!$C$13:$BJ$13,1)),"mmm-yy")&")") -> Month 46 (May-30) | C22: =IF(MAX('Team - Monthly Model'!$C$13:$BJ$13)<50000,"Not reached in 5 yrs","Month "&(MATCH(50000,'Team - Monthly Model'!$C$13:$BJ$13,1)+1)&" ("&TEXT(EDATE(DATE(2026,8,1),MATCH(50000,'Team - Monthly Model'!$C$13:$BJ$13,1)),"mmm-yy")&")") -> Month 34 (May-29)
A23: First month MRR reaches $100,000 | B23: =IF(MAX('Solo - Monthly Model'!$C$13:$BJ$13)<100000,"Not reached in 5 yrs","Month "&(MATCH(100000,'Solo - Monthly Model'!$C$13:$BJ$13,1)+1)&" ("&TEXT(EDATE(DATE(2026,8,1),MATCH(100000,'Solo - Monthly Model'!$C$13:$BJ$13,1)),"mmm-yy")&")") -> Not reached in 5 yrs | C23: =IF(MAX('Team - Monthly Model'!$C$13:$BJ$13)<100000,"Not reached in 5 yrs","Month "&(MATCH(100000,'Team - Monthly Model'!$C$13:$BJ$13,1)+1)&" ("&TEXT(EDATE(DATE(2026,8,1),MATCH(100000,'Team - Monthly Model'!$C$13:$BJ$13,1)),"mmm-yy")&")") -> Month 47 (Jun-30)
A24: First month net income turns positive ('breakeven') | B24: =IFERROR("Month "&MATCH(1,'Solo - Monthly Model'!$C$27:$BJ$27,0)&" ("&TEXT(EDATE(DATE(2026,8,1),MATCH(1,'Solo - Monthly Model'!$C$27:$BJ$27,0)-1),"mmm-yy")&")","Not within 5 yrs") -> Month 1 (Aug-26) | C24: =IFERROR("Month "&MATCH(1,'Team - Monthly Model'!$C$27:$BJ$27,0)&" ("&TEXT(EDATE(DATE(2026,8,1),MATCH(1,'Team - Monthly Model'!$C$27:$BJ$27,0)-1),"mmm-yy")&")","Not within 5 yrs") -> Month 1 (Aug-26) | E24: Marks when monthly revenue first covers that month's costs — not a guarantee it stays positive every month after (a new hire or slow month could dip it briefly).
A26: Read this as a planning tool, not a forecast: the single most sensitive input is the new-customer-adds ramp on the Assumptions tab — halving it roughly doubles every milestone month above. Update it as soon as you have real signup data.
